pycofbuilder/__init__.py
pycofbuilder/building_block.py
pycofbuilder/cjson.py
pycofbuilder/exceptions.py
pycofbuilder/framework.py
pycofbuilder/geometry.py
pycofbuilder/io_tools.py
pycofbuilder/logger.py
pycofbuilder/tools.py
pycofbuilder/data/__init__.py
pycofbuilder/data/periodic_table.json
pycofbuilder/data/topology.py
pycofbuilder/data/__pycache__/__init__.cpython-310.pyc
pycofbuilder/data/__pycache__/__init__.cpython-311.pyc
pycofbuilder/data/__pycache__/__init__.cpython-312.pyc
pycofbuilder/data/__pycache__/__init__.cpython-313.pyc
pycofbuilder/data/__pycache__/__init__.cpython-39.pyc
pycofbuilder/data/__pycache__/topology.cpython-310.pyc
pycofbuilder/data/__pycache__/topology.cpython-311.pyc
pycofbuilder/data/__pycache__/topology.cpython-312.pyc
pycofbuilder/data/__pycache__/topology.cpython-313.pyc
pycofbuilder/data/__pycache__/topology.cpython-39.pyc
pycofbuilder/data/conector/BOH2.cjson
pycofbuilder/data/conector/Br.cjson
pycofbuilder/data/conector/CCH3O.cjson
pycofbuilder/data/conector/CH2CN.cjson
pycofbuilder/data/conector/CH3.cjson
pycofbuilder/data/conector/CHNNH2.cjson
pycofbuilder/data/conector/CHO.cjson
pycofbuilder/data/conector/COCHCHOH.cjson
pycofbuilder/data/conector/CONHNH2.cjson
pycofbuilder/data/conector/COOH.cjson
pycofbuilder/data/conector/Cl.cjson
pycofbuilder/data/conector/NH2.cjson
pycofbuilder/data/conector/NHOH.cjson
pycofbuilder/data/conector/O.cjson
pycofbuilder/data/conector/OH2.cjson
pycofbuilder/data/conector/__init__.py
pycofbuilder/data/core/__init__.py
pycofbuilder/data/core/D4/ADAM.cjson
pycofbuilder/data/core/D4/CUBA.cjson
pycofbuilder/data/core/D4/SBFE.cjson
pycofbuilder/data/core/D4/TDAT.cjson
pycofbuilder/data/core/D4/TKAT.cjson
pycofbuilder/data/core/D4/TKDM.cjson
pycofbuilder/data/core/D4/TTPM.cjson
pycofbuilder/data/core/D4/__init__.py
pycofbuilder/data/core/H6/HECO.cjson
pycofbuilder/data/core/H6/HEXB.cjson
pycofbuilder/data/core/H6/HPCO.cjson
pycofbuilder/data/core/H6/__init__.py
pycofbuilder/data/core/L2/2BPD.cjson
pycofbuilder-0.0.9.4.dist-info/licenses/LICENSE
pycofbuilder-0.0.9.4.dist-info/METADATA
pycofbuilder-0.0.9.4.dist-info/WHEEL
pycofbuilder-0.0.9.4.dist-info/top_level.txt
pycofbuilder-0.0.9.4.dist-info/RECORD
