Metadata-Version: 2.4
Name: pycofbuilder
Version: 0.0.9.4
Summary: A package for Covalent Organic Frameworks sturcture creation based on the reticular approach.
Home-page: https://github.com/lipelopesoliveira/pyCOFBuilder
Author: Felipe Lopes Oliveira
Author-email: Felipe Lopes <felipe.lopes@nano.ufrj.br>
License: MIT License
Project-URL: Homepage, https://github.com/lipelopesoliveira/pyCOFBuilder
Project-URL: Issues, https://github.com/lipelopesoliveira/pyCOFBuilder/issues
Project-URL: Documentation, https://lipelopesoliveira.github.io/pyCOFBuilder/docs/_build/html/index.html
Classifier: Programming Language :: Python
Classifier: Programming Language :: Python :: 3
Classifier: Programming Language :: Python :: 3.10
Classifier: Intended Audience :: Science/Research
Classifier: Operating System :: OS Independent
Classifier: Topic :: Scientific/Engineering :: Information Analysis
Classifier: Topic :: Scientific/Engineering :: Physics
Classifier: Topic :: Scientific/Engineering :: Chemistry
Classifier: Topic :: Software Development :: Libraries :: Python Modules
Requires-Python: >=3.10
License-File: LICENSE
Dynamic: author
Dynamic: home-page
Dynamic: license-file
